apollo_fpga/__init__.py
apollo_fpga/ecp5.py
apollo_fpga/ila.py
apollo_fpga/intel.py
apollo_fpga/jtag.py
apollo_fpga/onboard_jtag.py
apollo_fpga/spi.py
apollo_fpga/commands/__init__.py
apollo_fpga/commands/cli.py
apollo_fpga/gateware/__init__.py
apollo_fpga/gateware/advertiser.py
apollo_fpga/gateware/flash_bridge.py
apollo_fpga/protocol/__init__.py
apollo_fpga/protocol/jtag_svf.py
apollo_fpga/support/__init__.py
apollo_fpga/support/bits.py
apollo_fpga/support/selftest.py
apollo_fpga-1.1.1.dist-info/LICENSE
apollo_fpga-1.1.1.dist-info/METADATA
apollo_fpga-1.1.1.dist-info/WHEEL
apollo_fpga-1.1.1.dist-info/entry_points.txt
apollo_fpga-1.1.1.dist-info/top_level.txt
apollo_fpga-1.1.1.dist-info/RECORD
