Metadata-Version: 2.1
Name: apollo-fpga
Version: 1.1.1
Summary: Python library and host tools for Apollo FPGA debug controllers.
Author-email: Great Scott Gadgets <dev@greatscottgadgets.com>
License: BSD
Project-URL: repository, https://github.com/greatscottgadgets/apollo
Project-URL: issues, https://github.com/greatscottgadgets/apollo/issues
Classifier: Programming Language :: Python
Classifier: Development Status :: 5 - Production/Stable
Classifier: Natural Language :: English
Classifier: Environment :: Console
Classifier: Environment :: Plugins
Classifier: Intended Audience :: Developers
Classifier: Intended Audience :: Science/Research
Classifier: License :: OSI Approved :: BSD License
Classifier: Operating System :: OS Independent
Classifier: Topic :: Scientific/Engineering
Requires-Python: >=3.8
License-File: LICENSE
Requires-Dist: pyusb >1.1.1
Requires-Dist: pyvcd >=0.2.4
Requires-Dist: prompt-toolkit >3.0.16
Requires-Dist: pyxdg >=0.27
Requires-Dist: deprecation >=2.1.0
Requires-Dist: importlib-resources ; python_version < "3.9"
